<?xml version="1.0" encoding="UTF-8"?>
<addon id="repository.luckyclover" name="LuckiyClover Add-ons Repository" version="1.0" provider-name="LuckiyClover">
    <extension point="xbmc.addon.repository" name="LuckiyClover Repository">
        <dir>
            <info compressed="false">https://raw.githubusercontent.com/LuckiyClover153/MyKodiRepo/main/addons/plugin.program.cmanwizard/addons.xml</info>
            <checksum>https://raw.githubusercontent.com/LuckiyClover153/MyKodiRepo/main/addons/plugin.program.cmanwizard/addonsmd5.txt</checksum>
            <datadir zip="true">https://raw.githubusercontent.com/LuckiyClover153/MyKodiRepo/main/addons/plugin.program.cmanwizard/zips/</datadir>
        </dir>
    </extension>

    <extension point="xbmc.addon.metadata">
        <summary>Community Add-ons and Builds</summary>
        <description>Install your favorite community builds and add-ons from the LuckiyClover Repository.</description>
        <platform>all</platform>
        <assets>
            <icon>icon.png</icon>
            <fanart>fanart.jpg</fanart>
        </assets>
    </extension>
</addon>
